qantify/__init__.py
qantify/backtest/__init__.py
qantify/backtest/advanced_analytics.py
qantify/backtest/advanced_orders.py
qantify/backtest/analytics.py
qantify/backtest/batch.py
qantify/backtest/benchmarking.py
qantify/backtest/compliance.py
qantify/backtest/costs.py
qantify/backtest/errors.py
qantify/backtest/event.py
qantify/backtest/execution.py
qantify/backtest/live_integration.py
qantify/backtest/multi_timeframe.py
qantify/backtest/orchestration.py
qantify/backtest/orders.py
qantify/backtest/portfolio.py
qantify/backtest/portfolio_optimization.py
qantify/backtest/reporting.py
qantify/backtest/risk.py
qantify/backtest/risk_engine.py
qantify/backtest/scenarios.py
qantify/backtest/scheduler.py
qantify/backtest/types.py
qantify/backtest/vectorized.py
qantify/backtest/walk_forward.py
qantify/backtest/engines/__init__.py
qantify/backtest/engines/async_event.py
qantify/backtest/engines/incremental.py
qantify/backtest/engines/parallel.py
qantify/backtest/market_microstructure/__init__.py
qantify/backtest/market_microstructure/detection.py
qantify/backtest/market_microstructure/queue.py
qantify/backtest/market_microstructure/replay.py
qantify/backtest/market_microstructure/simulator.py
qantify/compliance/__init__.py
qantify/compliance/audit_trail.py
qantify/compliance/compliance_monitoring.py
qantify/compliance/kyc_aml.py
qantify/compliance/position_reporting.py
qantify/compliance/regulatory_reporting.py
qantify/compliance/risk_reporting.py
qantify/compliance/transaction_reporting.py
qantify/core/__init__.py
qantify/core/types.py
qantify/core/utils.py
qantify/data/__init__.py
qantify/data/base.py
qantify/data/cache.py
qantify/data/errors.py
qantify/data/normalizers_alt.py
qantify/data/pipeline.py
qantify/data/registry.py
qantify/data/streaming.py
qantify/data/clients/__init__.py
qantify/data/clients/alpaca.py
qantify/data/clients/binance.py
qantify/data/clients/binance_futures.py
qantify/data/clients/dukascopy.py
qantify/data/clients/footfall.py
qantify-0.1.1.dist-info/licenses/LICENSE
qantify-0.1.1.dist-info/METADATA
qantify-0.1.1.dist-info/WHEEL
qantify-0.1.1.dist-info/top_level.txt
qantify-0.1.1.dist-info/RECORD
