Metadata-Version: 2.4
Name: qantify
Version: 0.1.1
Summary: High-performance, flexible quantitative trading toolkit
Author: qantify contributors
License: Qantify Dual License
Requires-Python: >=3.10
License-File: LICENSE
Requires-Dist: aiohttp>=3.9
Requires-Dist: numpy>=1.24
Requires-Dist: pandas>=2.0
Requires-Dist: scipy>=1.10
Requires-Dist: pyyaml>=6.0
Requires-Dist: python-dotenv>=1.0
Requires-Dist: pytz
Provides-Extra: timeseries
Requires-Dist: arch>=6.2; extra == "timeseries"
Requires-Dist: statsmodels>=0.14; extra == "timeseries"
Provides-Extra: io
Requires-Dist: pyarrow>=13.0; extra == "io"
Requires-Dist: fastparquet>=2023.10; extra == "io"
Requires-Dist: polars>=0.19; extra == "io"
Requires-Dist: lz4>=4.3; extra == "io"
Provides-Extra: ml
Requires-Dist: scikit-learn>=1.3; extra == "ml"
Requires-Dist: scikit-optimize>=0.9; extra == "ml"
Requires-Dist: hyperopt>=0.2; extra == "ml"
Requires-Dist: xgboost>=1.7; extra == "ml"
Requires-Dist: lightgbm>=4.0; extra == "ml"
Requires-Dist: shap>=0.42; extra == "ml"
Provides-Extra: dl
Requires-Dist: tensorflow>=2.13; extra == "dl"
Requires-Dist: torch>=2.1; extra == "dl"
Requires-Dist: transformers>=4.33; extra == "dl"
Provides-Extra: llm
Requires-Dist: openai>=1.0; extra == "llm"
Requires-Dist: anthropic>=0.7; extra == "llm"
Requires-Dist: google-generativeai>=0.3; extra == "llm"
Provides-Extra: optim
Requires-Dist: cvxpy>=1.4; extra == "optim"
Provides-Extra: prob
Requires-Dist: pymc>=5.6; extra == "prob"
Provides-Extra: monitoring
Requires-Dist: prometheus-client>=0.18; extra == "monitoring"
Requires-Dist: python-telegram-bot>=20.0; extra == "monitoring"
Provides-Extra: data
Requires-Dist: influxdb-client>=1.41; extra == "data"
Requires-Dist: redis>=5.0; extra == "data"
Requires-Dist: pymongo>=4.6; extra == "data"
Requires-Dist: boto3>=1.34; extra == "data"
Requires-Dist: cryptography>=42.0; extra == "data"
Requires-Dist: feast>=0.40; extra == "data"
Provides-Extra: plot
Requires-Dist: plotly>=5.18; extra == "plot"
Requires-Dist: matplotlib>=3.7; extra == "plot"
Provides-Extra: streaming
Requires-Dist: websockets>=11.0; extra == "streaming"
Provides-Extra: utils
Requires-Dist: tenacity>=8.2; extra == "utils"
Requires-Dist: tqdm>=4.65; extra == "utils"
Requires-Dist: dateparser>=1.2; extra == "utils"
Provides-Extra: dev
Requires-Dist: pytest>=8.1; extra == "dev"
Requires-Dist: pytest-asyncio>=0.23; extra == "dev"
Requires-Dist: pytest-cov>=5.0; extra == "dev"
Requires-Dist: pytest-benchmark>=4.0; extra == "dev"
Requires-Dist: pytest-mock>=3.12; extra == "dev"
Requires-Dist: pytest-xdist>=3.5; extra == "dev"
Requires-Dist: black>=24.3; extra == "dev"
Requires-Dist: ruff>=0.5; extra == "dev"
Requires-Dist: mypy>=1.7; extra == "dev"
Requires-Dist: types-requests; extra == "dev"
Requires-Dist: types-python-dateutil; extra == "dev"
Provides-Extra: full
Requires-Dist: qantify[data,dl,io,llm,ml,monitoring,optim,plot,prob,streaming,timeseries,utils]; extra == "full"
Dynamic: license-file
